{
  "$defs": {
    "DocumentType": {
      "enum": [
        "LOAN",
        "BANK_STATEMENT",
        "UNKNOWN"
      ],
      "title": "DocumentType",
      "type": "string"
    },
    "LoanExtractionSchema": {
      "description": "Schema for extracting loan details from a document.",
      "properties": {
        "name": {
          "description": "The name of the loan or lender",
          "title": "Name",
          "type": "string"
        },
        "principal": {
          "description": "The original principal amount of the loan",
          "title": "Principal",
          "type": "number"
        },
        "interest_rate": {
          "description": "The annual interest rate as a percentage (e.g., 12.0)",
          "title": "Interest Rate",
          "type": "number"
        },
        "installment_amount": {
          "description": "The monthly or per-period installment amount",
          "title": "Installment Amount",
          "type": "number"
        },
        "duration_months": {
          "description": "The total duration of the loan in months",
          "title": "Duration Months",
          "type": "integer"
        },
        "start_date": {
          "anyOf": [
            {
              "format": "date",
              "type": "string"
            },
            {
              "type": "null"
            }
          ],
          "default": null,
          "description": "The start date of the loan in YYYY-MM-DD format",
          "title": "Start Date"
        },
        "currency": {
          "default": "PHP",
          "description": "The ISO 4217 currency code (e.g., PHP, USD, SGD)",
          "title": "Currency",
          "type": "string"
        },
        "interest_type": {
          "$ref": "#/$defs/LoanInterestType",
          "default": "Standard Amortized",
          "description": "The type of interest calculation"
        },
        "lender": {
          "anyOf": [
            {
              "type": "string"
            },
            {
              "type": "null"
            }
          ],
          "default": null,
          "description": "The name of the lending institution",
          "title": "Lender"
        },
        "confidence": {
          "default": 0.0,
          "description": "Confidence score from 0.0 to 1.0",
          "maximum": 1,
          "minimum": 0,
          "title": "Confidence",
          "type": "number"
        },
        "reasoning": {
          "default": "",
          "description": "Brief explanation of the extraction results",
          "title": "Reasoning",
          "type": "string"
        }
      },
      "required": [
        "name",
        "principal",
        "interest_rate",
        "installment_amount",
        "duration_months"
      ],
      "title": "LoanExtractionSchema",
      "type": "object"
    },
    "LoanInterestType": {
      "enum": [
        "Standard Amortized",
        "Interest-Only",
        "Add-on Interest",
        "Fixed Principal"
      ],
      "title": "LoanInterestType",
      "type": "string"
    },
    "StatementExtractionSchema": {
      "description": "Structured extraction of multiple transactions from a bank statement.",
      "properties": {
        "account_name": {
          "description": "The name of the account or institution",
          "title": "Account Name",
          "type": "string"
        },
        "statement_period": {
          "description": "The date range covered by the statement",
          "title": "Statement Period",
          "type": "string"
        },
        "transactions": {
          "items": {
            "$ref": "#/$defs/TransactionExtractionItem"
          },
          "title": "Transactions",
          "type": "array"
        },
        "confidence": {
          "default": 0.0,
          "description": "Confidence score from 0.0 to 1.0",
          "maximum": 1,
          "minimum": 0,
          "title": "Confidence",
          "type": "number"
        },
        "reasoning": {
          "default": "",
          "description": "Brief explanation of the extraction results",
          "title": "Reasoning",
          "type": "string"
        }
      },
      "required": [
        "account_name",
        "statement_period",
        "transactions"
      ],
      "title": "StatementExtractionSchema",
      "type": "object"
    },
    "TransactionExtractionItem": {
      "description": "A single transaction extracted from a bank statement.",
      "properties": {
        "date": {
          "description": "The transaction date in YYYY-MM-DD format",
          "title": "Date",
          "type": "string"
        },
        "description": {
          "description": "The transaction description or merchant name",
          "title": "Description",
          "type": "string"
        },
        "amount": {
          "description": "The transaction amount (negative for expenses, positive for income/deposits)",
          "title": "Amount",
          "type": "number"
        }
      },
      "required": [
        "date",
        "description",
        "amount"
      ],
      "title": "TransactionExtractionItem",
      "type": "object"
    }
  },
  "description": "Polymorphic response for unified document processing.",
  "properties": {
    "document_type": {
      "$ref": "#/$defs/DocumentType",
      "description": "The classified type of the document"
    },
    "loan_data": {
      "anyOf": [
        {
          "$ref": "#/$defs/LoanExtractionSchema"
        },
        {
          "type": "null"
        }
      ],
      "default": null,
      "description": "Populated if document_type is LOAN"
    },
    "statement_data": {
      "anyOf": [
        {
          "$ref": "#/$defs/StatementExtractionSchema"
        },
        {
          "type": "null"
        }
      ],
      "default": null,
      "description": "Populated if document_type is BANK_STATEMENT"
    },
    "confidence": {
      "default": 0.0,
      "description": "Classification confidence",
      "maximum": 1,
      "minimum": 0,
      "title": "Confidence",
      "type": "number"
    },
    "reasoning": {
      "default": "",
      "description": "Reasoning for classification",
      "title": "Reasoning",
      "type": "string"
    },
    "ocr_telemetry": {
      "anyOf": [
        {
          "additionalProperties": true,
          "type": "object"
        },
        {
          "type": "null"
        }
      ],
      "default": null,
      "description": "Technical metadata about the extraction process (char counts, method)",
      "title": "Ocr Telemetry"
    }
  },
  "required": [
    "document_type"
  ],
  "title": "UnifiedDocumentResponse",
  "type": "object"
}